acsets/__init__.py
acsets/acsets.py
acsets/mira.py
acsets/petris.py
acsets/py.typed
acsets/schemas/__init__.py
acsets/schemas/catlab_to_jsonschema.py
acsets/schemas/catlab/LabelledPetriNet.json
acsets/schemas/catlab/LabelledReactionNet.json
acsets/schemas/catlab/PetriNet.json
acsets/schemas/catlab/PropertyLabelledPetriNet.json
acsets/schemas/catlab/PropertyLabelledReactionNet.json
acsets/schemas/catlab/PropertyPetriNet.json
acsets/schemas/catlab/PropertyReactionNet.json
acsets/schemas/catlab/ReactionNet.json
acsets/schemas/catlab/SummationDecapode.json
acsets/schemas/examples/README.md
acsets/schemas/jsonschema/LabelledPetriNet.json
acsets/schemas/jsonschema/LabelledReactionNet.json
acsets/schemas/jsonschema/PetriNet.json
acsets/schemas/jsonschema/PropertyLabelledPetriNet.json
acsets/schemas/jsonschema/PropertyLabelledReactionNet.json
acsets/schemas/jsonschema/PropertyPetriNet.json
acsets/schemas/jsonschema/PropertyReactionNet.json
acsets/schemas/jsonschema/ReactionNet.json
acsets/schemas/jsonschema/SummationDecapode.json
acsets-0.0.2.dist-info/LICENSE
acsets-0.0.2.dist-info/METADATA
acsets-0.0.2.dist-info/WHEEL
acsets-0.0.2.dist-info/top_level.txt
acsets-0.0.2.dist-info/RECORD
