Metadata-Version: 2.1
Name: acsets
Version: 0.0.2
Summary: Access to ACSets through python.
Home-page: https://github.com/AlgebraicJulia/py-acsets
Download-URL: https://github.com/AlgebraicJulia/py-acsets/releases
Author: Owen Lynch
Author-email: owen@topos.institute
Maintainer: Owen Lynch
Maintainer-email: owen@topos.institute
License: MIT
Project-URL: Bug Tracker, https://github.com/AlgebraicJulia/py-acsets/issues
Project-URL: Source Code, https://github.com/AlgebraicJulia/py-acsets
Keywords: snekpack,cookiecutter
Classifier: Development Status :: 1 - Planning
Classifier: Environment :: Console
Classifier: Intended Audience :: Developers
Classifier: License :: OSI Approved :: MIT License
Classifier: Operating System :: OS Independent
Classifier: Framework :: Pytest
Classifier: Framework :: tox
Classifier: Framework :: Sphinx
Classifier: Programming Language :: Python
Classifier: Programming Language :: Python :: 3.9
Classifier: Programming Language :: Python :: 3.10
Classifier: Programming Language :: Python :: 3.11
Classifier: Programming Language :: Python :: 3 :: Only
Requires-Python: >=3.9
License-File: LICENSE
Requires-Dist: pydantic
Provides-Extra: docs
Requires-Dist: sphinx ; extra == 'docs'
Requires-Dist: sphinx-rtd-theme ; extra == 'docs'
Requires-Dist: sphinx-autodoc-typehints ; extra == 'docs'
Requires-Dist: sphinx-automodapi ; extra == 'docs'
Provides-Extra: tests
Requires-Dist: pytest ; extra == 'tests'
Requires-Dist: coverage ; extra == 'tests'
Requires-Dist: jsonschema ; extra == 'tests'
